{
    "id": "fe3454b7-9855-4441-a000-7eba6c3d02b6",
    "name": "Sync Test 1773222733179",
    "mode": "advanced",
    "database": 6,
    "isGlobal": true,
    "tables": [
        {
            "name": "Duplicaten zoeken voor tblDeelnameAfspraken",
            "alias": "d",
            "joins": [],
            "relationships": []
        }
    ],
    "fields": [
        {
            "table": "Duplicaten zoeken voor tblDeelnameAfspraken",
            "field": "fkDeelname Veld",
            "dataType": 200,
            "visible": false,
            "showTotal": false
        },
        {
            "table": "Duplicaten zoeken voor tblDeelnameAfspraken",
            "field": "Context Veld",
            "dataType": 200,
            "visible": true,
            "showTotal": false
        },
        {
            "table": "Duplicaten zoeken voor tblDeelnameAfspraken",
            "field": "Subcontext Veld",
            "dataType": 200,
            "visible": true,
            "showTotal": false
        },
        {
            "table": "Duplicaten zoeken voor tblDeelnameAfspraken",
            "field": "fkLoginGeplaatstDoor Veld",
            "dataType": 200,
            "visible": false,
            "showTotal": false
        },
        {
            "table": "Duplicaten zoeken voor tblDeelnameAfspraken",
            "field": "AantalDuplicaten",
            "dataType": 200,
            "visible": true,
            "showTotal": false
        }
    ],
    "conditions": [],
    "parameters": [],
    "sorting": [],
    "grouping": [],
    "distinct": false,
    "topN": null,
    "totals": {
        "showGrandTotal": false,
        "fields": []
    },
    "output": {
        "format": "table"
    },
    "layout": {
        "tablePositions": [],
        "tableAliases": [],
        "tableSizes": [],
        "panelPosition": null
    },
    "updatedAt": "2026-03-11 09:52:15",
    "createdAt": "2026-03-11 09:52:15"
}